drf_audit_trail/__init__.py
drf_audit_trail/admin.py
drf_audit_trail/api/views.py
drf_audit_trail/apps.py
drf_audit_trail/database_router.py
drf_audit_trail/fields.py
drf_audit_trail/integrations/__init__.py
drf_audit_trail/integrations/rest_framework_authenticators.py
drf_audit_trail/integrations/rest_framework_simplejwt.py
drf_audit_trail/managers/__init__.py
drf_audit_trail/managers/login_audit_event_manager.py
drf_audit_trail/managers/request_audit_event_manager.py
drf_audit_trail/middleware/__init__.py
drf_audit_trail/middleware/request_login_audit_event.py
drf_audit_trail/migrations/0001_initial.py
drf_audit_trail/migrations/0002_requestauditevent_request_body_and_more.py
drf_audit_trail/migrations/0003_alter_requestauditevent_error_type_and_more.py
drf_audit_trail/migrations/__init__.py
drf_audit_trail/mixins.py
drf_audit_trail/models/__init__.py
drf_audit_trail/models/login_audit_event.py
drf_audit_trail/models/process_audit_event.py
drf_audit_trail/models/request_audit_event.py
drf_audit_trail/process_audit.py
drf_audit_trail/settings.py
drf_audit_trail/templates/performance_graph.html
drf_audit_trail/templates/report_pdf.html
drf_audit_trail/templatetags/__init__.py
drf_audit_trail/templatetags/custom_filter.py
drf_audit_trail/tests.py
drf_audit_trail/utils.py
drf_audit_trail/views.py
drf_audit_trail-0.4.3.dist-info/METADATA
drf_audit_trail-0.4.3.dist-info/WHEEL
drf_audit_trail-0.4.3.dist-info/licenses/LICENSE
drf_audit_trail-0.4.3.dist-info/RECORD
