Metadata-Version: 2.4
Name: drf-audit-trail
Version: 0.4.3
Summary: A reusable django [DRF] application that handles auditing of requests, logins and process
License-File: LICENSE
Author: Talismar Fernandes Costa
Author-email: talismar788.una@gmail.com
Requires-Python: >=3.10,<4.0
Classifier: Programming Language :: Python :: 3
Classifier: Programming Language :: Python :: 3.10
Classifier: Programming Language :: Python :: 3.11
Classifier: Programming Language :: Python :: 3.12
Classifier: Programming Language :: Python :: 3.13
Classifier: Programming Language :: Python :: 3.14
Requires-Dist: django (>=4.0)
Requires-Dist: djangorestframework (>=3.14.0,<4.0.0)
Requires-Dist: djangorestframework-simplejwt (>=5.2.2,<6.0.0)
Requires-Dist: weasyprint (>=62.3,<63.0)
Project-URL: Repository, https://github.com/Talismar/drf-audit-trail
